pdfrssdl/__init__.py
pdfrssdl/downloader.py
pdf_rss_dl-0.0.2.dist-info/METADATA
pdf_rss_dl-0.0.2.dist-info/WHEEL
pdf_rss_dl-0.0.2.dist-info/entry_points.txt
pdf_rss_dl-0.0.2.dist-info/top_level.txt
pdf_rss_dl-0.0.2.dist-info/RECORD
