Metadata-Version: 2.1
Name: pdf-rss-dl
Version: 0.0.2
Summary: A tool to download and export RSS feed entries as PDFs
Home-page: https://github.com/thisisawesome1994/pdf-rss-downloader
Author: Joannes J.A. Wyckmans
Author-email: johan.wyckmans@gmail.com
Classifier: Programming Language :: Python :: 3
Classifier: Operating System :: OS Independent
Requires-Python: >=3.7
Requires-Dist: fpdf
Requires-Dist: feedparser
